langchain_looker_agent/__init__.py
langchain_looker_agent/agent.py
langchain_looker_agent-0.1.5.dist-info/licenses/LICENSE
langchain_looker_agent-0.1.5.dist-info/METADATA
langchain_looker_agent-0.1.5.dist-info/WHEEL
langchain_looker_agent-0.1.5.dist-info/top_level.txt
langchain_looker_agent-0.1.5.dist-info/RECORD
