Metadata-Version: 2.4
Name: langchain-looker-agent
Version: 0.1.5
Summary: A LangChain SQL agent for querying Looker via its Open SQL Interface (JDBC/Avatica).
Author-email: Mark Rittman <mark.rittman@rittmananalytics.com>
License: Apache-2.0
Project-URL: Homepage, https://github.com/rittmananalytics/langchain-looker-sql-agent
Project-URL: Repository, https://github.com/rittmananalytics/langchain-looker-sql-agent.git
Project-URL: Issues, https://github.com/rittmananalytics/langchain-looker-sql-agent/issues
Keywords: langchain,looker,sql,agent,llm,conversational bi,jdbc,avatica
Classifier: Development Status :: 3 - Alpha
Classifier: Intended Audience :: Developers
Classifier: License :: OSI Approved :: Apache Software License
Classifier: Programming Language :: Python :: 3
Classifier: Programming Language :: Python :: 3.8
Classifier: Programming Language :: Python :: 3.9
Classifier: Programming Language :: Python :: 3.10
Classifier: Programming Language :: Python :: 3.11
Classifier: Topic :: Scientific/Engineering :: Artificial Intelligence
Classifier: Topic :: Database :: Front-Ends
Classifier: Topic :: Software Development :: Libraries :: Python Modules
Requires-Python: >=3.8
License-File: LICENSE
Requires-Dist: langchain-core>=0.1.52
Requires-Dist: langchain-community>=0.0.38
Requires-Dist: langchain>=0.1.20
Requires-Dist: jaydebeapi>=1.2.3
Requires-Dist: JPype1>=1.4.0
Dynamic: license-file
